control_unit.v
`timescale 1ns / 1ps

// ============================================================
// ISA — 16-bit instruction word, 8-bit datapath, 8 registers R0–R7
// ============================================================
// FORMATS
//   R  [15:12]=0000  [11:9]=rd  [8:6]=rs1  [5:3]=rs2  [2:0]=func
//   I  [15:12]=op    [11:9]=rd  [8:6]=rs1  [5:0]=imm6 (signed)
//   J  [15:12]=op    [11:9]=rd  [8:0]=imm9 (signed)
//
// OPCODES                                    status
//   0000 R-type ALU (func below)             done
//   0001 ADDI  rd = rs1 + sext(imm6)         done, tb in progress
//   0010 LDI   rd = sext(imm9)               todo
//   0011 LD    rd = MEM[rs1 + imm6]          todo
//   0100 ST    MEM[rs1 + imm6] = rd          todo
//   0101 BEQ   if rs1==rs2  PC += imm6       todo
//   0110 BNE   if rs1!=rs2  PC += imm6       todo
//   0111 BLT   if rs1< rs2  PC += imm6       todo
//   1000 JAL   rd = PC+1;   PC += imm9       todo
//
// R-TYPE FUNC [2:0]  (fed straight to ALU opcode)
//   000 ADD  rs1+rs2     100 XOR  rs1^rs2
//   001 SUB  rs1-rs2     101 NOT  ~rs1        (rs2 ignored)
//   010 AND  rs1&rs2     110 SHL  rs1<<1      (rs2 ignored)
//   011 OR   rs1|rs2     111 SHR  rs1>>1      (rs2 ignored)
//
// MICROARCH: multi-cycle, 3 states / R-type instruction
//   FETCH -> REG-READ (latch A,B) -> EXEC+WB (ALU, write rd, PC++)
// Harvard: instruction ROM addressed by PC; data memory separate (todo).
// ============================================================

module control_unit (
    input        clk,
    input        initial_rst,
    input  [2:0] dbg_addr,
    output [7:0] dbg_data
);

    // setup PC and IR
    reg [5:0] program_counter;   // 5-bit PC allows 32 words in ROM
    reg [15:0] instruction_reg;  // 16-bit IR for 16-bit word length
    wire [3:0] opcode = instruction_reg[15:12];
    reg [1:0] state; // state register

    // initialize ALU and regfile
    reg [7:0] alu_a, alu_b;
    reg [2:0] alu_opcode;
    wire [7:0] alu_result;
    wire [3:0] alu_flags;

    alu u_alu (
        .A     (alu_a),
        .B     (alu_b),
        .opcode(alu_opcode),
        .result(alu_result),
        .flags (alu_flags)
    );

    reg reg_write_en;
    reg [2:0] reg_read1_addr, reg_read2_addr, reg_write_addr;
    reg [7:0] reg_write_data;
    wire [7:0] reg_read1_data, reg_read2_data;

    regfile u_regfile (
        .clk       (clk),
        .rst       (initial_rst),
        .write_en  (reg_write_en),
        .read1_addr(reg_read1_addr),
        .read2_addr(reg_read2_addr),
        .read3_addr(dbg_addr),
        .write_addr(reg_write_addr),
        .write_data(reg_write_data),
        .read1_data(reg_read1_data),
        .read2_data(reg_read2_data),
        .read3_data(dbg_data)
    );

    // instantiate ROM module, input is hard-wired to PC
    wire [15:0] u_rom_read_data;

    rom u_rom (
        .rom_read_addr(program_counter),
        .rom_read_data(u_rom_read_data)
    );

    // Combinational logic selecting modules' inputs
    always @(*) begin
        case (opcode)
            // ADD DEFAULTS
            // R-type
            4'b0: begin
                reg_read1_addr = instruction_reg[8:6];
                reg_read2_addr = instruction_reg[5:3];
                alu_opcode = instruction_reg[2:0];
                if (state == 2'b10) reg_write_en = 1;
                else reg_write_en = 0;
                reg_write_addr = instruction_reg[11:9];
                reg_write_data = alu_result;
            end
            4'b0001: begin
                reg_read1_addr = instruction_reg[8:6];
                alu_opcode = 3'b0;
                if (state == 2'b10) reg_write_en = 1;
                else reg_write_en = 0;
                reg_write_addr = instruction_reg[11:9];
                reg_write_data = alu_result;
            end
        endcase
    end

    // Sequential Logic updating registers and FFs
    always @(posedge clk) begin

        if (initial_rst) begin
            instruction_reg <= 0;
            program_counter <= 0;
            state <= 0;
        end else begin
            case (state)
                // FETCH Phase
                2'b0: begin
                    instruction_reg <= u_rom_read_data;
                    state <= 2'b01; // go to decode phase
                end

                // DECODE Phase (reading registers, )
                2'b01: begin
                    case (opcode)
                        // R-type
                        4'b0: begin
                            alu_a <= reg_read1_data;
                            alu_b <= reg_read2_data;
                            state <= 2'b10;
                        end
                        4'b0001: begin
                            alu_a <= reg_read1_data;
                            alu_b <= {{2{instruction_reg[5]}}, {instruction_reg[5:0]}};  // imm6 padded to 8 bit
                            state <= 2'b10;
                        end
                    endcase
                end

                // EXECUTE_WB Phase
                2'b10: begin
                    case (opcode)
                        4'b0, 4'b0001: begin
                            state <= 2'b0;
                            program_counter <= program_counter + 1;
                        end
                    endcase
                end
            endcase
        end
    end
endmodule



module rom (
    input  [ 5:0] rom_read_addr,
    output [15:0] rom_read_data
);

    // IMPORTANT: Finish actual memory contents later!

    reg [15:0] memcells[0:31];
    initial begin
        $readmemh("prog.hex", memcells);
    end


    assign rom_read_data = memcells[rom_read_addr];

endmodule

regfile.v
`timescale 1ns / 1ps

module regfile (
    input        clk,
    input        rst,         // initial reset, active-high
    input        write_en,
    input  [2:0] read1_addr,  // 1 mem cell to read from
    input  [2:0] read2_addr,  // 2 mem cell to read from
    input  [2:0] read3_addr,  // 3 mem cell to read from, for LEDs
    input  [2:0] write_addr,  // write address
    input  [7:0] write_data,  // data input for write
    output [7:0] read1_data,  // output from cell 1
    output [7:0] read2_data   // output from cell 2
    output [7:0] read3_data   // output from mem cell 3, for LEDs
);

    reg [7:0] registers[0:7];  // initialize registers

    always @(posedge clk) begin
        integer i;  // for loop counter
        if (rst) begin
            for (i = 0; i < 8; i = i + 1) begin
                registers[i] <= 8'b0;
            end
        end else if (write_en) begin
            registers[write_addr] <= write_data;
        end
    end

    assign read1_data = registers[read1_addr];
    assign read2_data = registers[read2_addr];
    assign read3_data = registers[read3_addr]; // for LEDs

endmodule

rtl/alu.v
`timescale 1ns / 1ps

module adder_subtractor (
    input  [7:0] A,
    input  [7:0] B,
    input        ctrl,
    output [7:0] result,
    output       c_out,
    output       V
);
    // Two's complement: invert B and inject carry-in when subtracting
    wire [7:0] B_eff = ctrl ? ~B : B;
    wire       cin = ctrl;

    // Full 8-bit addition, temp[8] is c_out
    wire [8:0] temp = {1'b0, A} + {1'b0, B_eff} + cin;

    // Lower 7 bits only - temp1[7] is C_7 (carry into MSB)
    wire [7:0] temp1 = {1'b0, A[6:0]} + {1'b0, B_eff[6:0]} + cin;

    assign result = temp[7:0];
    assign c_out  = temp[8];
    assign V      = temp[8] ^ temp1[7];

endmodule

module alu (
    input      [7:0] A,
    input      [7:0] B,
    input      [2:0] opcode,
    output reg [7:0] result,
    output reg [3:0] flags
);

    // instantiate the adder-subtractor, OUTSIDE THE PROCEDURAL BLOCK
    wire [7:0] arithmetic_result;
    wire c_out, V;
    adder_subtractor u_add_sub (
        .A     (A),
        .B     (B),
        .ctrl  (opcode[0]),
        .result(arithmetic_result),
        .c_out (c_out),
        .V     (V)
    );

    always @(*) begin

        case (opcode)
            3'b000, 3'b001: result = arithmetic_result;  // same implementation - list with a comma
            3'b010:         result = A & B;
            3'b011:         result = A | B;
            3'b100:         result = A ^ B;
            3'b101:         result = ~A;
            3'b110:         result = A << 1;
            3'b111:         result = A >> 1;
            default: begin
                result = 8'b0;
                flags  = 4'b0;
            end
        endcase

        // flags calculation
        flags[0] = ~|result;  // zero flag, NOR all bits
        flags[1] = ~(opcode[1] | opcode[2]) & c_out;  // c_out flag
        flags[2] = result[7];  // sign flag
        flags[3] = ~(opcode[1] | opcode[2]) & V;  // overflow flag
    end

endmodule

// --indentation_spaces=4 --wrap_spaces=4 --column_limit=100 --port_declarations_alignment=align --port_declarations_indentation=indent --named_port_alignment=align --named_parameter_alignment=align --formal_parameters_alignment=align --formal_parameters_indentation=indent --module_net_variable_alignment=preserve --assignment_statement_alignment=preserve --case_items_alignment=align --class_member_variable_alignment=align --distribution_items_alignment=align --enum_assignment_statement_alignment=align --struct_union_members_alignment=align --try_wrap_long_lines=true

r_type_tb.v
`timescale 1ns / 1ps

// ============================================================
// Testbench for the R-type CPU (control_unit + alu + regfile + rom)
//
// Program under test lives in prog.hex:
//   ADD R3,R1,R2 / SUB R4,R1,R2 / AND R5,R1,R2 /
//   OR  R6,R1,R2 / XOR R7,R1,R2 / SHR R0,R1
//
// The regfile has no load instruction yet, so operands R1/R2 are
// seeded directly via a hierarchical force AFTER reset deasserts
// (reset clears the regfile, so seeding earlier would be wiped).
//
// Build & run:
//   iverilog -o cpu_test control_unit.v alu.v regfile.v cpu_tb.v
//   vvp cpu_test
//   gtkwave cpu_test.vcd
// (prog.hex must be in the working directory)
// ============================================================

module r_type_tb;

    reg clk;
    reg initial_rst;
    reg [2:0] dbg_addr;
    wire [7:0] dbg_data;
    integer i;

    // Device under test — control_unit instantiates alu, regfile, rom
    control_unit uut (
        .clk        (clk),
        .initial_rst(initial_rst),
        .dbg_addr   (dbg_addr),
        .dbg_data   (dbg_data)
    );

    // 10 ns clock
    initial clk = 0;
    always #5 clk = ~clk;

    // ---- reset, then seed operands ----
    initial begin
        $dumpfile("cpu_test.vcd");
        $dumpvars(0, r_type_tb);
        for (i = 0; i < 8; i = i + 1)  // dump regfile words for GTKWave
        $dumpvars(0, uut.u_regfile.registers[i]);

        // keep all switches off
        sw = 3'b0;

        initial_rst = 1;
        @(negedge clk);
        @(negedge clk);  // two posedges elapse with reset high
        initial_rst = 0;

        uut.u_regfile.registers[1] = 8'h0C;    // R1 = 12
        uut.u_regfile.registers[2] = 8'h05;    // R2 = 5
        $display("t=%0t  reset released; seeded R1=0x0C, R2=0x05", $time);
        $display("time  state  PC  IR    aluA aluB aluRes");
    end

    // ---- per-cycle trace (state: 0=FETCH 1=REG-READ 2=EXEC_WB) ----
    always @(posedge clk)
        if (!initial_rst)
            $display(
                "%4t   %0d    %0d  %h  %h   %h   %h",
                $time,
                uut.state,
                uut.program_counter,
                uut.instruction_reg,
                uut.alu_a,
                uut.alu_b,
                uut.alu_result
            );

    // ---- run long enough for 6 instrs x 3 cycles, then verify ----
    initial begin
        #250;
        $display("\n---- final register file ----");
        for (i = 0; i < 8; i = i + 1) $display("  R%0d = 0x%02h", i, uut.u_regfile.registers[i]);

        $display("\n---- checks ----");
        check(3'd0, 8'h06);  // SHR R0,R1  -> 0x0C >> 1
        check(3'd1, 8'h0C);  // seeded, untouched
        check(3'd2, 8'h05);  // seeded, untouched
        check(3'd3, 8'h11);  // ADD 12 + 5
        check(3'd4, 8'h07);  // SUB 12 - 5
        check(3'd5, 8'h04);  // AND 0x0C & 0x05
        check(3'd6, 8'h0D);  // OR  0x0C | 0x05
        check(3'd7, 8'h09);  // XOR 0x0C ^ 0x05

        $display("---- done ----");
        $finish;
    end

    task check;
        input [2:0] r;
        input [7:0] expected;
        begin
            if (uut.u_regfile.registers[r] === expected)
                $display("  PASS  R%0d = 0x%02h", r, expected);
            else
                $display(
                    "  FAIL  R%0d = 0x%02h  (expected 0x%02h)",
                    r,
                    uut.u_regfile.registers[r],
                    expected
                );
        end
    endtask

endmodule

dumps/cpu_test.vcd
$date
	Sat Aug  1 18:49:24 2026
$end
$version
	Icarus Verilog
$end
$timescale
	1ps
$end
$scope module r_type_tb $end
$var wire 8 ! dbg_data [7:0] $end
$var reg 1 " clk $end
$var reg 3 # dbg_addr [2:0] $end
$var reg 1 $ initial_rst $end
$var integer 32 % i [31:0] $end
$scope module uut $end
$var wire 1 " clk $end
$var wire 3 & dbg_addr [2:0] $end
$var wire 1 $ initial_rst $end
$var wire 16 ' u_rom_read_data [15:0] $end
$var wire 8 ( reg_read2_data [7:0] $end
$var wire 8 ) reg_read1_data [7:0] $end
$var wire 4 * opcode [3:0] $end
$var wire 8 + dbg_data [7:0] $end
$var wire 8 , alu_result [7:0] $end
$var wire 4 - alu_flags [3:0] $end
$var reg 8 . alu_a [7:0] $end
$var reg 8 / alu_b [7:0] $end
$var reg 3 0 alu_opcode [2:0] $end
$var reg 16 1 instruction_reg [15:0] $end
$var reg 6 2 program_counter [5:0] $end
$var reg 3 3 reg_read1_addr [2:0] $end
$var reg 3 4 reg_read2_addr [2:0] $end
$var reg 3 5 reg_write_addr [2:0] $end
$var reg 8 6 reg_write_data [7:0] $end
$var reg 1 7 reg_write_en $end
$var reg 2 8 state [1:0] $end
$scope module u_alu $end
$var wire 8 9 A [7:0] $end
$var wire 8 : B [7:0] $end
$var wire 3 ; opcode [2:0] $end
$var wire 1 < c_out $end
$var wire 8 = arithmetic_result [7:0] $end
$var wire 1 > V $end
$var reg 4 ? flags [3:0] $end
$var reg 8 @ result [7:0] $end
$scope module u_add_sub $end
$var wire 8 A A [7:0] $end
$var wire 8 B B [7:0] $end
$var wire 1 > V $end
$var wire 1 C cin $end
$var wire 1 D ctrl $end
$var wire 8 E temp1 [7:0] $end
$var wire 9 F temp [8:0] $end
$var wire 8 G result [7:0] $end
$var wire 1 < c_out $end
$var wire 8 H B_eff [7:0] $end
$upscope $end
$upscope $end
$scope module u_regfile $end
$var wire 1 " clk $end
$var wire 3 I read1_addr [2:0] $end
$var wire 8 J read1_data [7:0] $end
$var wire 3 K read2_addr [2:0] $end
$var wire 8 L read2_data [7:0] $end
$var wire 3 M read3_addr [2:0] $end
$var wire 8 N read3_data [7:0] $end
$var wire 1 $ rst $end
$var wire 3 O write_addr [2:0] $end
$var wire 8 P write_data [7:0] $end
$var wire 1 7 write_en $end
$scope begin $unm_blk_16 $end
$var integer 32 Q i [31:0] $end
$upscope $end
$upscope $end
$scope module u_rom $end
$var wire 6 R rom_read_addr [5:0] $end
$var wire 16 S rom_read_data [15:0] $end
$upscope $end
$upscope $end
$scope task check $end
$var reg 8 T expected [7:0] $end
$var reg 3 U r [2:0] $end
$upscope $end
$upscope $end
$scope module r_type_tb $end
$scope module uut $end
$scope module u_regfile $end
$var reg 8 V \registers[0] [7:0] $end
$upscope $end
$upscope $end
$upscope $end
$scope module r_type_tb $end
$scope module uut $end
$scope module u_regfile $end
$var reg 8 W \registers[1] [7:0] $end
$upscope $end
$upscope $end
$upscope $end
$scope module r_type_tb $end
$scope module uut $end
$scope module u_regfile $end
$var reg 8 X \registers[2] [7:0] $end
$upscope $end
$upscope $end
$upscope $end
$scope module r_type_tb $end
$scope module uut $end
$scope module u_regfile $end
$var reg 8 Y \registers[3] [7:0] $end
$upscope $end
$upscope $end
$upscope $end
$scope module r_type_tb $end
$scope module uut $end
$scope module u_regfile $end
$var reg 8 Z \registers[4] [7:0] $end
$upscope $end
$upscope $end
$upscope $end
$scope module r_type_tb $end
$scope module uut $end
$scope module u_regfile $end
$var reg 8 [ \registers[5] [7:0] $end
$upscope $end
$upscope $end
$upscope $end
$scope module r_type_tb $end
$scope module uut $end
$scope module u_regfile $end
$var reg 8 \ \registers[6] [7:0] $end
$upscope $end
$upscope $end
$upscope $end
$scope module r_type_tb $end
$scope module uut $end
$scope module u_regfile $end
$var reg 8 ] \registers[7] [7:0] $end
$upscope $end
$upscope $end
$upscope $end
$enddefinitions $end
$comment Show the parameter values. $end
$dumpall
$end
#0
$dumpvars
bx ]
bx \
bx [
bx Z
bx Y
bx X
bx W
bx V
bx U
bx T
bx S
bx R
bx Q
bx P
bx O
bx N
b0 M
bx L
bx K
bx J
bx I
bx H
bx G
bx F
bx E
xD
xC
bx B
bx A
bx @
bx ?
x>
bx =
x<
bx ;
bx :
bx 9
bx 8
x7
bx 6
bx 5
bx 4
bx 3
bx 2
bx 1
bx 0
bx /
bx .
bx -
bx ,
bx +
bx *
bx )
bx (
bx '
b0 &
b1000 %
1$
b0 #
0"
bx !
$end
#5000
0C
0D
b0 5
b0 O
07
b0 0
b0 ;
b0 (
b0 L
b0 4
b0 K
b0 )
b0 J
b0 3
b0 I
b0 *
b0 ]
b0 \
b0 [
b0 Z
b0 Y
b0 X
b0 W
b0 V
b0 !
b0 +
b0 N
b0 8
b11001010000 '
b11001010000 S
b0 2
b0 R
b0 1
b1000 Q
1"
#10000
0"
#15000
b0 ]
b0 \
b0 [
b0 Z
b0 Y
b0 X
b0 W
b0 V
b1000 Q
1"
#20000
b101 X
b1100 W
0$
0"
#25000
b11 5
b11 O
b101 (
b101 L
b10 4
b10 K
b1100 )
b1100 J
b1 3
b1 I
b1 8
b11001010000 1
1"
#30000
0"
#35000
b10001 6
b10001 P
b0 -
b0 ?
b10001 ,
b10001 @
0>
b10001 =
b10001 G
0<
b10001 E
17
b10001 F
b101 H
b10 8
b101 /
b101 :
b101 B
b1100 .
b1100 9
b1100 A
1"
#40000
0"
#45000
07
b10001 Y
b100001010001 '
b100001010001 S
b1 2
b1 R
b0 8
1"
#50000
0"
#55000
b111 6
b111 P
b10 -
b10 ?
b111 ,
b111 @
1<
b111 =
b111 G
b11111010 H
b100000111 F
b10000111 E
1C
1D
b100 5
b100 O
b1 0
b1 ;
b1 8
b100001010001 1
1"
#60000
0"
#65000
17
b10 8
1"
#70000
0"
#75000
07
b111 Z
b101001010010 '
b101001010010 S
b10 2
b10 R
b0 8
1"
#80000
0"
#85000
0<
b100 6
b100 P
b10001 =
b10001 G
b101 H
b0 -
b0 ?
b100 ,
b100 @
b10001 F
b10001 E
0C
0D
b101 5
b101 O
b10 0
b10 ;
b1 8
b101001010010 1
1"
#90000
0"
#95000
17
b10 8
1"
#100000
0"
#105000
07
b100 [
b110001010011 '
b110001010011 S
b11 2
b11 R
b0 8
1"
#110000
0"
#115000
1<
b1101 6
b1101 P
b111 =
b111 G
b11111010 H
b1101 ,
b1101 @
b100000111 F
b10000111 E
1C
1D
b110 5
b110 O
b11 0
b11 ;
b1 8
b110001010011 1
1"
#120000
0"
#125000
17
b10 8
1"
#130000
0"
#135000
07
b1101 \
b111001010100 '
b111001010100 S
b100 2
b100 R
b0 8
1"
#140000
0"
#145000
0<
b1001 6
b1001 P
b10001 =
b10001 G
b101 H
b1001 ,
b1001 @
b10001 F
b10001 E
0C
0D
b111 5
b111 O
b100 0
b100 ;
b1 8
b111001010100 1
1"
#150000
0"
#155000
17
b10 8
1"
#160000
0"
#165000
07
b1001 ]
b1000111 '
b1000111 S
b101 2
b101 R
b0 8
1"
#170000
0"
#175000
1<
b110 6
b110 P
b111 =
b111 G
b11111010 H
b110 ,
b110 @
b100000111 F
b10000111 E
1C
1D
b0 5
b0 O
b111 0
b111 ;
b0 (
b0 L
b0 4
b0 K
b1 8
b1000111 1
1"
#180000
0"
#185000
b1100 =
b1100 G
b10001100 E
b100001100 F
b11111111 H
17
b10 8
b0 /
b0 :
b0 B
1"
#190000
0"
#195000
07
b110 V
b110 (
b110 L
b110 !
b110 +
b110 N
bx '
bx S
b110 2
b110 R
b0 8
1"
#200000
0"
#205000
bx *
b1 8
bx 1
1"
#210000
0"
#215000
1"
#220000
0"
#225000
1"
#230000
0"
#235000
1"
#240000
0"
#245000
1"
#250000
0"
b1001 T
b111 U
b1000 %
